{
  "_comment": "Ediciones próximas (aún no en pokemontcg.io). Lista curada a mano. Logo desde pokemon.com (patrón estable: .../series/<serie>_series/<id>/<id>_logo_169_en.png). Actualiza al anunciarse una nueva.",
  "upcoming": [
    {
      "id": "me05",
      "name": "Pitch Black",
      "series": "Mega Evolution",
      "releaseDate": "2026/07/17",
      "logo": "https://www.pokemon.com/static-assets/content-assets/cms2/img/trading-card-game/series/me_series/me05/me05_logo_169_en.png",
      "url": "https://www.pokemon.com/us/pokemon-tcg/mega-evolution-pitch-black"
    }
  ]
}
